LICENSE
MANIFEST.in
README.md
requirements.txt
setup.py
dreamerv3/__init__.py
dreamerv3/agent.py
dreamerv3/behaviors.py
dreamerv3/configs.yaml
dreamerv3/expl.py
dreamerv3/jaxagent.py
dreamerv3/jaxutils.py
dreamerv3/nets.py
dreamerv3/ninjax.py
dreamerv3/train.py
dreamerv3.egg-info/PKG-INFO
dreamerv3.egg-info/SOURCES.txt
dreamerv3.egg-info/dependency_links.txt
dreamerv3.egg-info/requires.txt
dreamerv3.egg-info/top_level.txt
dreamerv3/embodied/__init__.py
dreamerv3/embodied/core/__init__.py
dreamerv3/embodied/core/base.py
dreamerv3/embodied/core/basics.py
dreamerv3/embodied/core/batch.py
dreamerv3/embodied/core/batcher.py
dreamerv3/embodied/core/checkpoint.py
dreamerv3/embodied/core/config.py
dreamerv3/embodied/core/counter.py
dreamerv3/embodied/core/distr.py
dreamerv3/embodied/core/driver.py
dreamerv3/embodied/core/flags.py
dreamerv3/embodied/core/logger.py
dreamerv3/embodied/core/metrics.py
dreamerv3/embodied/core/parallel.py
dreamerv3/embodied/core/path.py
dreamerv3/embodied/core/prefetch.py
dreamerv3/embodied/core/random.py
dreamerv3/embodied/core/space.py
dreamerv3/embodied/core/timer.py
dreamerv3/embodied/core/uuid.py
dreamerv3/embodied/core/when.py
dreamerv3/embodied/core/worker.py
dreamerv3/embodied/core/wrappers.py
dreamerv3/embodied/envs/atari.py
dreamerv3/embodied/envs/crafter.py
dreamerv3/embodied/envs/dmc.py
dreamerv3/embodied/envs/dmlab.py
dreamerv3/embodied/envs/dummy.py
dreamerv3/embodied/envs/from_dm.py
dreamerv3/embodied/envs/from_gym.py
dreamerv3/embodied/envs/loconav.py
dreamerv3/embodied/envs/loconav_quadruped.py
dreamerv3/embodied/envs/minecraft.py
dreamerv3/embodied/envs/minecraft_base.py
dreamerv3/embodied/envs/minecraft_minerl.py
dreamerv3/embodied/envs/pinpad.py
dreamerv3/embodied/envs/robodesk.py
dreamerv3/embodied/replay/__init__.py
dreamerv3/embodied/replay/chunk.py
dreamerv3/embodied/replay/generic.py
dreamerv3/embodied/replay/limiters.py
dreamerv3/embodied/replay/naive_chunks.py
dreamerv3/embodied/replay/replays.py
dreamerv3/embodied/replay/reverb.py
dreamerv3/embodied/replay/saver.py
dreamerv3/embodied/replay/selectors.py
dreamerv3/embodied/run/__init__.py
dreamerv3/embodied/run/eval_only.py
