Metadata-Version: 2.1
Name: dreamerv3
Version: 1.5.0
Summary: Mastering Diverse Domains through World Models
Home-page: http://github.com/danijar/dreamerv3
Classifier: Intended Audience :: Science/Research
Classifier: License :: OSI Approved :: MIT License
Classifier: Programming Language :: Python :: 3
Classifier: Topic :: Scientific/Engineering :: Artificial Intelligence
License-File: LICENSE
